<annotation verified="yes">
	<folder>training</folder>
	<filename>020.jpg</filename>
	<path>E:\Projects\Dongchongxiacao\training\020.jpg</path>
	<source>
		<database>Unknown</database>
	</source>
	<size>
		<width>800</width>
		<height>400</height>
		<depth>3</depth>
	</size>
	<segmented>0</segmented>
	<object>
		<name>Chongcao</name>
		<pose>Unspecified</pose>
		<truncated>0</truncated>
		<difficult>0</difficult>
		<bndbox>
			<xmin>380</xmin>
			<ymin>142</ymin>
			<xmax>464</xmax>
			<ymax>310</ymax>
		</bndbox>
	</object>
</annotation>
